vocaltractlab/__init__.py
vocaltractlab/audioprocessing.py
vocaltractlab/contour.py
vocaltractlab/core.py
vocaltractlab/frequency_domain.py
vocaltractlab/tube_state.py
vocaltractlab/utils.py
vocaltractlab/avl/__init__.py
vocaltractlab/avl/core.py
vocaltractlab/avl/sample.py
vocaltractlab/avl/sensory_optimization.py
vocaltractlab/avl/synthesize.py
vocaltractlab/avl/vtl_core.py
vocaltractlab/avl/woa.py
vocaltractlab-0.5.8.dist-info/licenses/LICENSE.md
vocaltractlab-0.5.8.dist-info/METADATA
vocaltractlab-0.5.8.dist-info/WHEEL
vocaltractlab-0.5.8.dist-info/top_level.txt
vocaltractlab-0.5.8.dist-info/RECORD
