Metadata-Version: 2.4
Name: VocalTractLab
Version: 0.5.8
Summary: High-performance articulatory speech synthesis in Python
Home-page: https://github.com/paul-krug/VocalTractLab-Python
Author: Paul Krug
License: GPL-3.0
Keywords: text-to-speech,speech synthesis,articulatory synthesis,vocal tract,speech production,vocoder
License-File: LICENSE.md
Requires-Dist: numpy
Requires-Dist: target-approximation>=0.0.4
Requires-Dist: tools-mp==0.2.0
Requires-Dist: torch
Requires-Dist: torchaudio
Requires-Dist: vocaltractlab-cython==0.0.16
Dynamic: author
Dynamic: description
Dynamic: description-content-type
Dynamic: home-page
Dynamic: keywords
Dynamic: license
Dynamic: license-file
Dynamic: requires-dist
Dynamic: summary
